Workbook

Sheet Raw Messy Data
A1: Invoice | B1: StockCode | C1: Description | D1: Quantity | E1: InvoiceDate | F1: Price | G1: Customer ID | H1: Country
A2: 503181 | B2: 84792 | C2: ENCHANTED BIRD COATHANGER 5 HOOK | D2: 4 | E2: 40267.599 | F2: 4.65 | H2: United Kingdom
A3: 528386 | B3: 22318 | C3: FIVE HEART HANGING DECORATION | D3: 6 | E3: 40472.772 | F3: 2.95 | G3: 14911 | H3: EIRE
A4: 498594 | B4: 21173 | C4: LOO ROLL METAL SIGN | D4: 1 | E4: 40230.658 | F4: 1.65 | G4: 16797 | H4: United Kingdom
A5: 503245 | B5: 21777 | C5: RECIPE BOX WITH METAL HEART | D5: 2 | E5: 40268.411 | F5: 7.95 | G5: 15216 | H5: United Kingdom
A6: 505756 | B6: 84836 | C6: ZINC METAL HEART DECORATION | D6: 12 | E6: 40294.408 | F6: 1.25 | G6: 14677 | H6: United Kingdom
A7: 496975 | B7: 21559 | C7: STRAWBERRY LUNCHBOX WITH CUTLERY | D7: 6 | E7: 40214.385 | F7: 2.55 | G7: 12712 | H7: Germany
A8: 491584 | B8: 85107 | C8: CUT GLASS T-LIGHT HOLDER OCTAGON | D8: 12 | E8: 40158.538 | F8: 2.55 | G8: 12854 | H8: United Kingdom
A9: 516478 | B9: 22575 | C9: METAL MERRY CHRISTMAS WREATH | D9: 1 | E9: 40379.722 | F9: 1.95 | G9: 17576 | H9: United Kingdom
A10: 502588 | B10: 22083 | C10: PAPER CHAIN KIT RETRO SPOT | D10: 2 | E10: 40262.53 | F10: 2.95 | G10: 16550 | H10: United Kingdom
A11: 515335 | B11: 85014B | C11: RED/WHITE DOTS RUFFLED UMBRELLA | D11: 1 | E11: 40370.597 | F11: 5.95 | G11: 14606 | H11: United Kingdom
A12: 525065 | B12: 21156 | C12: RETROSPOT CHILDRENS APRON | D12: 1 | E12: 40454.603 | F12: 1.95 | G12: 16799 | H12: United Kingdom
A13: 535349 | B13: 84946 | C13: ANTIQUE SILVER TEA GLASS ETCHED | D13: 24 | E13: 40507.703 | F13: 1.25 | G13: 18245 | H13: United Kingdom
A14: 521949 | B14: 82484 | C14: WOOD BLACK BOARD ANT WHITE FINISH | D14: 3 | E14: 40430.719 | F14: 6.45 | G14: 15150 | H14: United Kingdom
A15: 514876 | B15: 22519 | C15: CHILDS GARDEN BRUSH PINK | D15: 36 | E15: 40366.44 | F15: 1.85 | G15: 17511 | H15: United Kingdom
A16: 521162 | B16: 22561 | C16: WOODEN SCHOOL COLOURING SET | D16: 12 | E16: 40423.599 | F16: 1.65 | G16: 12598 | H16: France
A17: 506572 | B17: 20798 | C17: CLEAR MILKSHAKE GLASS | D17: 4 | E17: 40298.549 | F17: 2.1 | G17: 16374 | H17: United Kingdom
A18: 505974 | B18: 48188 | C18: DOOR MAT WELCOME PUPPIES | D18: 1 | E18: 40294.754 | F18: 7.49 | G18: 17449 | H18: United Kingdom
A19: 491622 | B19: 10125 | C19: MINI FUNKY DESIGN TAPES | D19: 1 | E19: 40158.597 | F19: 0.85 | G19: 13415 | H19: U.K.
A20: 509982 | B20: 21696 | C20: SMALL SILVER TRELLIS CANDLEPOT | D20: 6 | E20: 40324.603 | F20: 2.95 | G20: 12924 | H20: United Kingdom
A21: 524611 | B21: 85114B | C21: IVORY ENCHANTED FOREST PLACEMAT | D21: 6 | E21: 40451.401 | F21: 1.65 | G21: 13078 | H21: United Kingdom
A22: 501906 | B22: 22413 | C22: METAL SIGN TAKE IT OR LEAVE IT | D22: 12 | E22: 40258.668 | F22: 2.95 | G22: 17340 | H22: United Kingdom
A23: 505708 | B23: 20979 | C23: 36 PENCILS TUBE RED SPOTTY | D23: 1 | E23: 40293.51 | F23: 1.25 | G23: 13782 | H23: United Kingdom
A24: 497935 | B24: 79323W | C24: WHITE CHERRY LIGHTS | D24: 24 | E24: 40224.449 | F24: 5.45 | G24: 13408 | H24: United Kingdom
A25: 502792 | B25: 15044C | C25: PURPLE PAPER PARASOL | D25: 6 | E25: 40263.631 | F25: 2.95 | G25: 14253 | H25: United Kingdom
A26: 521403 | B26: 21179 | D26: 12 | E26: 40427.43 | F26: 1.25 | G26: 12744 | H26: Singapore
A27: 522904 | B27: 72529W | C27: WHITE ADVENT CANDLE | D27: 1 | E27: 40438.531 | F27: 2.12 | G27: 17765 | H27: United Kingdom
A28: 537810 | B28: 22415 | C28: WHITE TISSUE REAM | D28: 3 | E28: 08-12-2010 13:30 | F28: 7.95 | G28: 15032 | H28: United Kingdom
A29: 520505 | B29: 21258 | C29: VICTORIAN SEWING BOX LARGE | D29: 1 | E29: 40416.535 | F29: 12.75 | G29: 17663 | H29: United Kingdom
A30: 533067 | B30: 21122 | C30: SET/10 PINK POLKADOT PARTY CANDLES | D30: 24 | E30: 40497.718 | F30: 1.25 | G30: 17284 | H30: United Kingdom
A31: 523971 | B31: 21009 | C31: ETCHED GLASS STAR TREE DECORATION | D31: 6 | E31: 40447.578 | F31: 1.25 | G31: 15967 | H31: United Kingdom
A32: 499625 | B32: 15056BL | C32: EDWARDIAN PARASOL BLACK | D32: 2 | E32: 40238.551 | F32: 5.95 | G32: 17965 | H32: United Kingdom
A33: 500147 | B33: 47566 | C33: PARTY BUNTING | D33: 8 | E33: 40241.724 | F33: 4.65 | G33: 15812 | H33: United Kingdom
A34: 537421 | B34: 22569 | C34: FELTCRAFT CUSHION BUTTERFLY | D34: 2 | E34: 40518.642 | F34: 3.75 | G34: 17218 | H34: UNITED KINGDOM
A35: 534526 | B35: 21930 | C35: JUMBO STORAGE BAG SKULLS | D35: 10 | E35: 40505.503 | F35: 1.95 | G35: 15384 | H35: United Kingdom
A36: 503164 | B36: 22556 | C36: PLASTERS IN TIN CIRCUS PARADE | D36: 1 | E36: 40267.552 | F36: 1.65 | G36: 17464 | H36: United Kingdom
A37: 528618 | B37: 21499 | C37: BLUE POLKADOT WRAP | D37: 25 | E37: 40473.713 | F37: 0.42 | G37: 13263 | H37: United Kingdom
A38: 505015 | B38: 22196 | C38: SMALL HEART MEASURING SPOONS | D38: 12 | E38: 40287.562 | F38: 0.85 | G38: 14156 | H38: EIRE
A39: 497272 | B39: 84510B | C39: SET OF 4 FAIRY CAKES COASTERS | D39: 10 | E39: 40217.576 | F39: 1.25 | G39: 17160 | H39: United Kingdom
A40: 518480 | B40: 21890 | C40: S/6 WOODEN SKITTLES IN COTTON BAG | D40: 2 | E40: 40399.515 | F40: 2.95 | G40: 16470 | H40: United Kingdom
A41: 508593 | B41: 21900 | C41: KEY FOB , SHED | D41: 24 | E41: 40315.504 | F41: 0.65 | G41: 13488 | H41: United Kingdom
A42: 505615 | B42: 20712 | C42: JUMBO BAG WOODLAND ANIMALS | D42: 10 | E42: 40291.534 | F42: 1.95 | G42: 15288 | H42: United Kingdom
A43: 523314 | B43: 22551 | C43: PLASTERS IN TIN SPACEBOY | D43: 1 | E43: 40442.558 | F43: 1.65 | H43: United Kingdom
A44: 530538 | B44: 21563 | C44: RED HEART SHAPE LOVE BUCKET | D44: 2 | E44: 40485.538 | F44: 2.95 | G44: 14606 | H44: United Kingdom
A45: 493706 | B45: 84832 | C45: ZINC WILLIE WINKIE CANDLE STICK | D45: 14 | E45: 40183.606 | F45: 0.85 | G45: 15768 | H45: United Kingdom
A46: 490823 | B46: 21847 | C46: GREEN DIAMANTE PEN IN GIFT BOX | D46: 24 | E46: 40155.524 | F46: 1.25 | G46: 14841 | H46: United Kingdom
A47: 506091 | B47: 21651 | C47: HANGING GLASS ETCHED TEALIGHT | D47: 6 | E47: 40295.508 | F47: 1.65 | G47: 15402 | H47: United Kingdom
A48: 494866 | B48: 22052 | C48: VINTAGE CARAVAN GIFT WRAP | D48: 25 | E48: 40197.472 | F48: 0.42 | G48: 16253 | H48: United Kingdom
A49: 498923 | B49: 84978 | C49: HANGING HEART JAR T-LIGHT HOLDER | D49: 12 | E49: 40233.41 | F49: 1.25 | G49: 17028 | H49: United Kingdom
A50: 516157 | B50: 21069 | D50: 1 | E50: 40377.492 | F50: 1.25 | G50: 17261 | H50: United Kingdom
A51: 509100 | B51: 22511 | C51: DOORSTOP RUSSIAN DOLL RETROSPOT | D51: 1 | E51: 40318.492 | F51: 3.75 | G51: 17841 | H51: United Kingdom
A52: C511560 | B52: 20914 | C52: SET/5 RED SPOTTY LID GLASS BOWLS | D52: -1 | E52: 40338.444 | F52: 2.95 | G52: 18231 | H52: United Kingdom
A53: 524746 | B53: 22752 | C53: SET 7 BABUSHKA NESTING BOXES | D53: 4 | E53: 40451.612 | F53: 8.5 | G53: 16859 | H53: United Kingdom
A54: 496821 | B54: 22236 | C54: CAKE STAND 3 TIER MAGIC GARDEN | D54: 2 | E54: 40213.442 | F54: 12.75 | G54: 13875 | H54: United Kingdom
A55: 513964 | B55: 22380 | C55: TOY TIDY SPACEBOY | D55: 20 | E55: 40358.637 | F55: 2.1 | G55: 12380 | H55: Belgium
A56: 501291 | B56: 84578 | C56: ELEPHANT TOY WITH BLUE T-SHIRT | D56: 1 | E56: 40252.648 | F56: 3.75 | G56: 14343 | H56: United Kingdom
A57: 525944 | B57: 71477 | C57: COLOUR GLASS. STAR T-LIGHT HOLDER | D57: 5 | E57: 40458.738 | F57: 3.25 | G57: 16059 | H57: United Kingdom
A58: 498577 | B58: 21892 | C58: TRADITIONAL WOODEN CATCH CUP GAME | D58: 12 | E58: 40230.575 | F58: 1.25 | G58: 16948 | H58: United kingdom
A59: 497958 | B59: 21156 | C59: RED SPOTTY CHILDS APRON | D59: 2 | E59: 40224.556 | F59: 1.95 | G59: 14680 | H59: United Kingdom
A60: 504152 | B60: 21622 | C60: VINTAGE UNION JACK CUSHION COVER | D60: 8 | E60: 40279.576 | F60: 4.95 | G60: 17838 | H60: United Kingdom
A61: 501657 | B61: 22328 | C61: ROUND SNACK BOXES SET OF 4 FRUITS | D61: 1 | E61: 40255.549 | F61: 2.95 | G61: 13243 | H61: United Kingdom
A62: 491816 | B62: 20862 | C62: PINK PATCH PENCIL CASE BLUE HEART | D62: 6 | E62: 40161.567 | F62: 2.1 | G62: 14961 | H62: United Kingdom
A63: 493960 | B63: 22024 | C63: RAINY LADIES BIRTHDAY CARD | D63: 24 | E63: 40186.626 | F63: 0.42 | G63: 16556 | H63: United Kingdom
A64: 531746 | B64: 22745 | C64: POPPY'S PLAYHOUSE BEDROOM | D64: 1 | E64: 40491.542 | F64: 2.1 | G64: 14527 | H64: United Kingdom
A65: 512093 | B65: 21731 | C65: RED TOADSTOOL LED NIGHT LIGHT | D65: 24 | E65: 40342.546 | F65: 1.65 | G65: 16954 | H65: United Kingdom
A66: 495576 | B66: 22355 | C66: CHARLOTTE BAG , SUKI DESIGN | D66: 10 | E66: 40204.403 | F66: 0.85 | G66: 15259 | H66: United Kingdom
A67: 506383 | B67: 21431 | C67: GREEN GINGHAM FLOWER JEWELLERY BOX | D67: 8 | E67: 40297.521 | F67: 1.65 | G67: 13824 | H67: United Kingdom
A68: 523097 | B68: 48138 | C68: DOORMAT UNION FLAG | D68: 3 | E68: 40441.515 | F68: 7.95 | G68: 17055 | H68: United Kingdom
A69: 534221 | B69: 22745 | C69: POPPY'S PLAYHOUSE BEDROOM | D69: 1 | E69: 40503.677 | F69: 2.1 | G69: 16049 | H69: United Kingdom
A70: 529763 | B70: 22118 | C70: JOY WOODEN BLOCK LETTERS | D70: 1 | E70: 40480.625 | F70: 4.95 | G70: 14081 | H70: United Kingdom
A71: 528417 | B71: 22665 | C71: RECIPE BOX BLUE SKETCHBOOK DESIGN | D71: 6 | E71: 40473.4 | F71: 2.95 | G71: 14156 | H71: EIRE
A72: 510232 | B72: 22605 | C72: WOODEN CROQUET GARDEN SET | D72: 3 | E72: 40326.403 | F72: 12.75 | G72: 15674 | H72: United Kingdom
A73: 528176 | B73: 72807C | C73: SET/3 VANILLA SCENTED CANDLE IN BOX | D73: 4 | E73: 40472.436 | F73: 4.25 | G73: 12725 | H73: Italy
A74: 528761 | B74: 22435 | C74: SET OF 9 HEART SHAPED BALLOONS | D74: 12 | E74: 40475.654 | F74: 1.25 | G74: 13898 | H74: United Kingdom
A75: 501284 | B75: 22321 | C75: BIRD DECORATION RED SPOT | D75: 24 | E75: 40252.597 | F75: 0.85 | G75: 12714 | H75: France
A76: 496703 | B76: 22076 | C76: 6 RIBBONS EMPIRE | D76: 12 | E76: 40212.557 | F76: 1.65 | G76: 12396 | H76: RSA
A77: 497946 | B77: 85198 | C77: ASSORTED FARMYARD ANIMALS IN BUCKET | D77: 3312 | E77: 40224.498 | F77: 0.3 | G77: 13902 | H77: Denmark
A78: 507178 | B78: 21121 | C78: SET/10 RED SPOTTY PARTY CANDLES | D78: 288 | E78: 40304.637 | F78: 1.06 | G78: 14646 | H78: Netherlands
A79: 516265 | B79: 22378 | C79: WALL TIDY RETROSPOT | D79: 1 | E79: 40378.505 | F79: 2.1 | G79: 16782 | H79: United Kingdom
A80: 505885 | B80: 21175 | C80: GIN + TONIC DIET METAL SIGN | D80: 12 | E80: 40294.586 | F80: 2.1 | G80: 16623 | H80: United Kingdom
A81: 510139 | B81: 21892 | C81: TRADITIONAL WOODEN CATCH CUP GAME | D81: 2 | E81: 40325.517 | F81: 1.25 | G81: 16695 | H81: United Kingdom
A82: 502628 | B82: 22262 | C82: FELT EGG COSY CHICKEN | D82: 12 | E82: 40262.65 | F82: 0.85 | G82: 16670 | H82: United Kingdom
A83: 511851 | B83: 48184 | C83: DOOR MAT ENGLISH ROSE | D83: 1 | E83: 40339.806 | F83: 7.49 | G83: 13542 | H83: United Kingdom
A84: 500326 | B84: 85206A | C84: CREAM FELT EASTER EGG BASKET | D84: 2 | E84: 40244.517 | F84: 1.65 | G84: 14877 | H84: United Kingdom
A85: 526089 | B85: 22294 | C85: HEART FILIGREE DOVE SMALL | D85: 24 | E85: 40459.51 | F85: 1.25 | G85: 15281 | H85: United Kingdom
A86: 518432 | B86: 21212 | C86: PACK OF 72 RETRO SPOT CAKE CASES | D86: 24 | E86: 40399.463 | F86: 0.55 | G86: 14625 | H86: United Kingdom
A87: 533547 | B87: 84380 | C87: SET OF 3 BUTTERFLY COOKIE CUTTERS | D87: 12 | E87: 40499.7 | F87: 1.25 | G87: 16409 | H87: United Kingdom
A88: 527754 | B88: 84580 | C88: MOUSE TOY WITH PINK T-SHIRT | D88: 2 | E88: 40469.712 | F88: 3.75 | G88: 15710 | H88: United Kingdom
A89: 496008 | B89: 21428 | C89: SET3 BOOK BOX GREEN GINGHAM FLOWER | D89: 4 | E89: 40206.525 | F89: 4.25 | G89: 14911 | H89: EIRE
A90: 509071 | B90: 84839 | C90: SWEETHEART KEY CABINET | D90: 2 | E90: 40318.487 | F90: 6.75 | G90: 16471 | H90: United Kingdom
A91: 535656 | B91: 21986 | C91: PACK OF 12 PINK POLKADOT TISSUES | D91: 3 | E91: 40510.472 | F91: 0.29 | G91: 16010 | H91: united kingdom
A92: 522885 | B92: 21535 | C92: RED RETROSPOT SMALL MILK JUG | D92: 6 | E92: 40438.504 | F92: 2.55 | G92: 13952 | H92: United Kingdom
A93: 502038 | B93: 20749 | C93: ASSORTED COLOUR MINI CASES | D93: 2 | E93: 40259.576 | F93: 7.95 | G93: 13206 | H93: United Kingdom
A94: 516132 | B94: 22139 | C94: RETRO SPOT TEA SET CERAMIC 11 PC | D94: 12 | E94: 40375.644 | F94: 4.95 | G94: 16767 | H94: United Kingdom
A95: 511500 | B95: 21216 | C95: SET 3 RED SPOT TIN TEA,COFFEE,SUGAR | D95: 4 | E95: 40337.614 | F95: 4.95 | G95: 14210 | H95: United Kingdom
A96: 518547 | B96: 21426 | C96: WOODLAND STORAGE BOX SMALL | D96: 96 | E96: 40399.771 | F96: 1.25 | G96: 18102 | H96: United KIngdom
A97: 501689 | B97: 22021 | C97: BLUE FELT EASTER EGG BASKET | D97: 12 | E97: 40255.712 | F97: 1.65 | G97: 15738 | H97: United Kingdom
A98: 489802 | B98: 85104 | C98: SILVER GLASS T-LIGHT SET | D98: 4 | E98: 40149.522 | F98: 2.95 | G98: 15581 | H98: United Kingdom
A99: 497364 | B99: 84997B | C99: RED 3 PIECE MINI DOTS CUTLERY SET | D99: 6 | E99: 40218.408 | F99: 3.75 | G99: 13131 | H99: United Kingdom
A100: 535332 | B100: 84879 | C100: ASSORTED COLOUR BIRD ORNAMENT | D100: 8 | E100: 40507.663 | F100: 1.69 | G100: 18161 | H100: United Kingdom
...

Sheet Clean Data
A1: Invoice | B1: StockCode | C1: Description | D1: Quantity | E1: InvoiceDate | F1: Price | G1: Customer ID | H1: Country | I1: Revenue
A2: 528386 | B2: 22318 | C2: FIVE HEART HANGING DECORATION | D2: 6 | E2: 40472.772 | F2: 2.95 | G2: 14911 | H2: Eire | I2: =(D2 *F2) -> 17.7
A3: 498594 | B3: 21173 | C3: LOO ROLL METAL SIGN | D3: 1 | E3: 40230.658 | F3: 1.65 | G3: 16797 | H3: United Kingdom | I3: =(D3 *F3) -> 1.65
A4: 503245 | B4: 21777 | C4: RECIPE BOX WITH METAL HEART | D4: 2 | E4: 40268.411 | F4: 7.95 | G4: 15216 | H4: United Kingdom | I4: =(D4 *F4) -> 15.9
A5: 505756 | B5: 84836 | C5: ZINC METAL HEART DECORATION | D5: 12 | E5: 40294.408 | F5: 1.25 | G5: 14677 | H5: United Kingdom | I5: =(D5 *F5) -> 15
A6: 496975 | B6: 21559 | C6: STRAWBERRY LUNCHBOX WITH CUTLERY | D6: 6 | E6: 40214.385 | F6: 2.55 | G6: 12712 | H6: Germany | I6: =(D6 *F6) -> 15.3
A7: 491584 | B7: 85107 | C7: CUT GLASS T-LIGHT HOLDER OCTAGON | D7: 12 | E7: 40158.538 | F7: 2.55 | G7: 12854 | H7: United Kingdom | I7: =(D7 *F7) -> 30.6
A8: 516478 | B8: 22575 | C8: METAL MERRY CHRISTMAS WREATH | D8: 1 | E8: 40379.722 | F8: 1.95 | G8: 17576 | H8: United Kingdom | I8: =(D8 *F8) -> 1.95
A9: 502588 | B9: 22083 | C9: PAPER CHAIN KIT RETRO SPOT | D9: 2 | E9: 40262.53 | F9: 2.95 | G9: 16550 | H9: United Kingdom | I9: =(D9 *F9) -> 5.9
A10: 515335 | B10: 85014B | C10: RED/WHITE DOTS RUFFLED UMBRELLA | D10: 1 | E10: 40370.597 | F10: 5.95 | G10: 14606 | H10: United Kingdom | I10: =(D10 *F10) -> 5.95
A11: 525065 | B11: 21156 | C11: RETROSPOT CHILDRENS APRON | D11: 1 | E11: 40454.603 | F11: 1.95 | G11: 16799 | H11: United Kingdom | I11: =(D11 *F11) -> 1.95
A12: 535349 | B12: 84946 | C12: ANTIQUE SILVER TEA GLASS ETCHED | D12: 24 | E12: 40507.703 | F12: 1.25 | G12: 18245 | H12: United Kingdom | I12: =(D12 *F12) -> 30
A13: 521949 | B13: 82484 | C13: WOOD BLACK BOARD ANT WHITE FINISH | D13: 3 | E13: 40430.719 | F13: 6.45 | G13: 15150 | H13: United Kingdom | I13: =(D13 *F13) -> 19.35
A14: 514876 | B14: 22519 | C14: CHILDS GARDEN BRUSH PINK | D14: 36 | E14: 40366.44 | F14: 1.85 | G14: 17511 | H14: United Kingdom | I14: =(D14 *F14) -> 66.6
A15: 521162 | B15: 22561 | C15: WOODEN SCHOOL COLOURING SET | D15: 12 | E15: 40423.599 | F15: 1.65 | G15: 12598 | H15: France | I15: =(D15 *F15) -> 19.8
A16: 506572 | B16: 20798 | C16: CLEAR MILKSHAKE GLASS | D16: 4 | E16: 40298.549 | F16: 2.1 | G16: 16374 | H16: United Kingdom | I16: =(D16 *F16) -> 8.4
A17: 505974 | B17: 48188 | C17: DOOR MAT WELCOME PUPPIES | D17: 1 | E17: 40294.754 | F17: 7.49 | G17: 17449 | H17: United Kingdom | I17: =(D17 *F17) -> 7.49
A18: 491622 | B18: 10125 | C18: MINI FUNKY DESIGN TAPES | D18: 1 | E18: 40158.597 | F18: 0.85 | G18: 13415 | H18: U.K. | I18: =(D18 *F18) -> 0.85
A19: 509982 | B19: 21696 | C19: SMALL SILVER TRELLIS CANDLEPOT | D19: 6 | E19: 40324.603 | F19: 2.95 | G19: 12924 | H19: United Kingdom | I19: =(D19 *F19) -> 17.7
A20: 524611 | B20: 85114B | C20: IVORY ENCHANTED FOREST PLACEMAT | D20: 6 | E20: 40451.401 | F20: 1.65 | G20: 13078 | H20: United Kingdom | I20: =(D20 *F20) -> 9.9
A21: 501906 | B21: 22413 | C21: METAL SIGN TAKE IT OR LEAVE IT | D21: 12 | E21: 40258.668 | F21: 2.95 | G21: 17340 | H21: United Kingdom | I21: =(D21 *F21) -> 35.4
A22: 505708 | B22: 20979 | C22: 36 PENCILS TUBE RED SPOTTY | D22: 1 | E22: 40293.51 | F22: 1.25 | G22: 13782 | H22: United Kingdom | I22: =(D22 *F22) -> 1.25
A23: 497935 | B23: 79323W | C23: WHITE CHERRY LIGHTS | D23: 24 | E23: 40224.449 | F23: 5.45 | G23: 13408 | H23: United Kingdom | I23: =(D23 *F23) -> 130.8
A24: 502792 | B24: 15044C | C24: PURPLE PAPER PARASOL | D24: 6 | E24: 40263.631 | F24: 2.95 | G24: 14253 | H24: United Kingdom | I24: =(D24 *F24) -> 17.7
A25: 522904 | B25: 72529W | C25: WHITE ADVENT CANDLE | D25: 1 | E25: 40438.531 | F25: 2.12 | G25: 17765 | H25: United Kingdom | I25: =(D25 *F25) -> 2.12
A26: 537810 | B26: 22415 | C26: WHITE TISSUE REAM | D26: 3 | E26: 40402.562 | F26: 7.95 | G26: 15032 | H26: United Kingdom | I26: =(D26 *F26) -> 23.85
A27: 520505 | B27: 21258 | C27: VICTORIAN SEWING BOX LARGE | D27: 1 | E27: 40416.535 | F27: 12.75 | G27: 17663 | H27: United Kingdom | I27: =(D27 *F27) -> 12.75
A28: 533067 | B28: 21122 | C28: SET/10 PINK POLKADOT PARTY CANDLES | D28: 24 | E28: 40497.718 | F28: 1.25 | G28: 17284 | H28: United Kingdom | I28: =(D28 *F28) -> 30
A29: 523971 | B29: 21009 | C29: ETCHED GLASS STAR TREE DECORATION | D29: 6 | E29: 40447.578 | F29: 1.25 | G29: 15967 | H29: United Kingdom | I29: =(D29 *F29) -> 7.5
A30: 499625 | B30: 15056BL | C30: EDWARDIAN PARASOL BLACK | D30: 2 | E30: 40238.551 | F30: 5.95 | G30: 17965 | H30: United Kingdom | I30: =(D30 *F30) -> 11.9
A31: 500147 | B31: 47566 | C31: PARTY BUNTING | D31: 8 | E31: 40241.724 | F31: 4.65 | G31: 15812 | H31: United Kingdom | I31: =(D31 *F31) -> 37.2
A32: 537421 | B32: 22569 | C32: FELTCRAFT CUSHION BUTTERFLY | D32: 2 | E32: 40518.642 | F32: 3.75 | G32: 17218 | H32: United Kingdom | I32: =(D32 *F32) -> 7.5
A33: 534526 | B33: 21930 | C33: JUMBO STORAGE BAG SKULLS | D33: 10 | E33: 40505.503 | F33: 1.95 | G33: 15384 | H33: United Kingdom | I33: =(D33 *F33) -> 19.5
A34: 503164 | B34: 22556 | C34: PLASTERS IN TIN CIRCUS PARADE | D34: 1 | E34: 40267.552 | F34: 1.65 | G34: 17464 | H34: United Kingdom | I34: =(D34 *F34) -> 1.65
A35: 528618 | B35: 21499 | C35: BLUE POLKADOT WRAP | D35: 25 | E35: 40473.713 | F35: 0.42 | G35: 13263 | H35: United Kingdom | I35: =(D35 *F35) -> 10.5
A36: 505015 | B36: 22196 | C36: SMALL HEART MEASURING SPOONS | D36: 12 | E36: 40287.562 | F36: 0.85 | G36: 14156 | H36: Eire | I36: =(D36 *F36) -> 10.2
A37: 497272 | B37: 84510B | C37: SET OF 4 FAIRY CAKES COASTERS | D37: 10 | E37: 40217.576 | F37: 1.25 | G37: 17160 | H37: United Kingdom | I37: =(D37 *F37) -> 12.5
A38: 518480 | B38: 21890 | C38: S/6 WOODEN SKITTLES IN COTTON BAG | D38: 2 | E38: 40399.515 | F38: 2.95 | G38: 16470 | H38: United Kingdom | I38: =(D38 *F38) -> 5.9
A39: 508593 | B39: 21900 | C39: KEY FOB , SHED | D39: 24 | E39: 40315.504 | F39: 0.65 | G39: 13488 | H39: United Kingdom | I39: =(D39 *F39) -> 15.6
A40: 505615 | B40: 20712 | C40: JUMBO BAG WOODLAND ANIMALS | D40: 10 | E40: 40291.534 | F40: 1.95 | G40: 15288 | H40: United Kingdom | I40: =(D40 *F40) -> 19.5
A41: 530538 | B41: 21563 | C41: RED HEART SHAPE LOVE BUCKET | D41: 2 | E41: 40485.538 | F41: 2.95 | G41: 14606 | H41: United Kingdom | I41: =(D41 *F41) -> 5.9
A42: 493706 | B42: 84832 | C42: ZINC WILLIE WINKIE CANDLE STICK | D42: 14 | E42: 40183.606 | F42: 0.85 | G42: 15768 | H42: United Kingdom | I42: =(D42 *F42) -> 11.9
A43: 490823 | B43: 21847 | C43: GREEN DIAMANTE PEN IN GIFT BOX | D43: 24 | E43: 40155.524 | F43: 1.25 | G43: 14841 | H43: United Kingdom | I43: =(D43 *F43) -> 30
A44: 506091 | B44: 21651 | C44: HANGING GLASS ETCHED TEALIGHT | D44: 6 | E44: 40295.508 | F44: 1.65 | G44: 15402 | H44: United Kingdom | I44: =(D44 *F44) -> 9.9
A45: 494866 | B45: 22052 | C45: VINTAGE CARAVAN GIFT WRAP | D45: 25 | E45: 40197.472 | F45: 0.42 | G45: 16253 | H45: United Kingdom | I45: =(D45 *F45) -> 10.5
A46: 498923 | B46: 84978 | C46: HANGING HEART JAR T-LIGHT HOLDER | D46: 12 | E46: 40233.41 | F46: 1.25 | G46: 17028 | H46: United Kingdom | I46: =(D46 *F46) -> 15
A47: 509100 | B47: 22511 | C47: DOORSTOP RUSSIAN DOLL RETROSPOT | D47: 1 | E47: 40318.492 | F47: 3.75 | G47: 17841 | H47: United Kingdom | I47: =(D47 *F47) -> 3.75
A48: C511560 | B48: 20914 | C48: SET/5 RED SPOTTY LID GLASS BOWLS | D48: -1 | E48: 40338.444 | F48: 2.95 | G48: 18231 | H48: United Kingdom | I48: =(D48 *F48) -> -2.95
A49: 524746 | B49: 22752 | C49: SET 7 BABUSHKA NESTING BOXES | D49: 4 | E49: 40451.612 | F49: 8.5 | G49: 16859 | H49: United Kingdom | I49: =(D49 *F49) -> 34
A50: 496821 | B50: 22236 | C50: CAKE STAND 3 TIER MAGIC GARDEN | D50: 2 | E50: 40213.442 | F50: 12.75 | G50: 13875 | H50: United Kingdom | I50: =(D50 *F50) -> 25.5
A51: 513964 | B51: 22380 | C51: TOY TIDY SPACEBOY | D51: 20 | E51: 40358.637 | F51: 2.1 | G51: 12380 | H51: Belgium | I51: =(D51 *F51) -> 42
A52: 501291 | B52: 84578 | C52: ELEPHANT TOY WITH BLUE T-SHIRT | D52: 1 | E52: 40252.648 | F52: 3.75 | G52: 14343 | H52: United Kingdom | I52: =(D52 *F52) -> 3.75
A53: 525944 | B53: 71477 | C53: COLOUR GLASS. STAR T-LIGHT HOLDER | D53: 5 | E53: 40458.738 | F53: 3.25 | G53: 16059 | H53: United Kingdom | I53: =(D53 *F53) -> 16.25
A54: 498577 | B54: 21892 | C54: TRADITIONAL WOODEN CATCH CUP GAME | D54: 12 | E54: 40230.575 | F54: 1.25 | G54: 16948 | H54: United Kingdom | I54: =(D54 *F54) -> 15
A55: 497958 | B55: 21156 | C55: RED SPOTTY CHILDS APRON | D55: 2 | E55: 40224.556 | F55: 1.95 | G55: 14680 | H55: United Kingdom | I55: =(D55 *F55) -> 3.9
A56: 504152 | B56: 21622 | C56: VINTAGE UNION JACK CUSHION COVER | D56: 8 | E56: 40279.576 | F56: 4.95 | G56: 17838 | H56: United Kingdom | I56: =(D56 *F56) -> 39.6
A57: 501657 | B57: 22328 | C57: ROUND SNACK BOXES SET OF 4 FRUITS | D57: 1 | E57: 40255.549 | F57: 2.95 | G57: 13243 | H57: United Kingdom | I57: =(D57 *F57) -> 2.95
A58: 491816 | B58: 20862 | C58: PINK PATCH PENCIL CASE BLUE HEART | D58: 6 | E58: 40161.567 | F58: 2.1 | G58: 14961 | H58: United Kingdom | I58: =(D58 *F58) -> 12.6
A59: 493960 | B59: 22024 | C59: RAINY LADIES BIRTHDAY CARD | D59: 24 | E59: 40186.626 | F59: 0.42 | G59: 16556 | H59: United Kingdom | I59: =(D59 *F59) -> 10.08
A60: 531746 | B60: 22745 | C60: POPPY'S PLAYHOUSE BEDROOM | D60: 1 | E60: 40491.542 | F60: 2.1 | G60: 14527 | H60: United Kingdom | I60: =(D60 *F60) -> 2.1
A61: 512093 | B61: 21731 | C61: RED TOADSTOOL LED NIGHT LIGHT | D61: 24 | E61: 40342.546 | F61: 1.65 | G61: 16954 | H61: United Kingdom | I61: =(D61 *F61) -> 39.6
A62: 495576 | B62: 22355 | C62: CHARLOTTE BAG , SUKI DESIGN | D62: 10 | E62: 40204.403 | F62: 0.85 | G62: 15259 | H62: United Kingdom | I62: =(D62 *F62) -> 8.5
A63: 506383 | B63: 21431 | C63: GREEN GINGHAM FLOWER JEWELLERY BOX | D63: 8 | E63: 40297.521 | F63: 1.65 | G63: 13824 | H63: United Kingdom | I63: =(D63 *F63) -> 13.2
A64: 523097 | B64: 48138 | C64: DOORMAT UNION FLAG | D64: 3 | E64: 40441.515 | F64: 7.95 | G64: 17055 | H64: United Kingdom | I64: =(D64 *F64) -> 23.85
A65: 534221 | B65: 22745 | C65: POPPY'S PLAYHOUSE BEDROOM | D65: 1 | E65: 40503.677 | F65: 2.1 | G65: 16049 | H65: United Kingdom | I65: =(D65 *F65) -> 2.1
A66: 529763 | B66: 22118 | C66: JOY WOODEN BLOCK LETTERS | D66: 1 | E66: 40480.625 | F66: 4.95 | G66: 14081 | H66: United Kingdom | I66: =(D66 *F66) -> 4.95
A67: 528417 | B67: 22665 | C67: RECIPE BOX BLUE SKETCHBOOK DESIGN | D67: 6 | E67: 40473.4 | F67: 2.95 | G67: 14156 | H67: Eire | I67: =(D67 *F67) -> 17.7
A68: 510232 | B68: 22605 | C68: WOODEN CROQUET GARDEN SET | D68: 3 | E68: 40326.403 | F68: 12.75 | G68: 15674 | H68: United Kingdom | I68: =(D68 *F68) -> 38.25
A69: 528176 | B69: 72807C | C69: SET/3 VANILLA SCENTED CANDLE IN BOX | D69: 4 | E69: 40472.436 | F69: 4.25 | G69: 12725 | H69: Italy | I69: =(D69 *F69) -> 17
A70: 528761 | B70: 22435 | C70: SET OF 9 HEART SHAPED BALLOONS | D70: 12 | E70: 40475.654 | F70: 1.25 | G70: 13898 | H70: United Kingdom | I70: =(D70 *F70) -> 15
A71: 501284 | B71: 22321 | C71: BIRD DECORATION RED SPOT | D71: 24 | E71: 40252.597 | F71: 0.85 | G71: 12714 | H71: France | I71: =(D71 *F71) -> 20.4
A72: 496703 | B72: 22076 | C72: 6 RIBBONS EMPIRE | D72: 12 | E72: 40212.557 | F72: 1.65 | G72: 12396 | H72: Rsa | I72: =(D72 *F72) -> 19.8
A73: 497946 | B73: 85198 | C73: ASSORTED FARMYARD ANIMALS IN BUCKET | D73: 3312 | E73: 40224.498 | F73: 0.3 | G73: 13902 | H73: Denmark | I73: =(D73 *F73) -> 993.6
A74: 507178 | B74: 21121 | C74: SET/10 RED SPOTTY PARTY CANDLES | D74: 288 | E74: 40304.637 | F74: 1.06 | G74: 14646 | H74: Netherlands | I74: =(D74 *F74) -> 305.28
A75: 516265 | B75: 22378 | C75: WALL TIDY RETROSPOT | D75: 1 | E75: 40378.505 | F75: 2.1 | G75: 16782 | H75: United Kingdom | I75: =(D75 *F75) -> 2.1
A76: 505885 | B76: 21175 | C76: GIN + TONIC DIET METAL SIGN | D76: 12 | E76: 40294.586 | F76: 2.1 | G76: 16623 | H76: United Kingdom | I76: =(D76 *F76) -> 25.2
A77: 510139 | B77: 21892 | C77: TRADITIONAL WOODEN CATCH CUP GAME | D77: 2 | E77: 40325.517 | F77: 1.25 | G77: 16695 | H77: United Kingdom | I77: =(D77 *F77) -> 2.5
A78: 502628 | B78: 22262 | C78: FELT EGG COSY CHICKEN | D78: 12 | E78: 40262.65 | F78: 0.85 | G78: 16670 | H78: United Kingdom | I78: =(D78 *F78) -> 10.2
A79: 511851 | B79: 48184 | C79: DOOR MAT ENGLISH ROSE | D79: 1 | E79: 40339.806 | F79: 7.49 | G79: 13542 | H79: United Kingdom | I79: =(D79 *F79) -> 7.49
A80: 500326 | B80: 85206A | C80: CREAM FELT EASTER EGG BASKET | D80: 2 | E80: 40244.517 | F80: 1.65 | G80: 14877 | H80: United Kingdom | I80: =(D80 *F80) -> 3.3
A81: 526089 | B81: 22294 | C81: HEART FILIGREE DOVE SMALL | D81: 24 | E81: 40459.51 | F81: 1.25 | G81: 15281 | H81: United Kingdom | I81: =(D81 *F81) -> 30
A82: 518432 | B82: 21212 | C82: PACK OF 72 RETRO SPOT CAKE CASES | D82: 24 | E82: 40399.463 | F82: 0.55 | G82: 14625 | H82: United Kingdom | I82: =(D82 *F82) -> 13.2
A83: 533547 | B83: 84380 | C83: SET OF 3 BUTTERFLY COOKIE CUTTERS | D83: 12 | E83: 40499.7 | F83: 1.25 | G83: 16409 | H83: United Kingdom | I83: =(D83 *F83) -> 15
A84: 527754 | B84: 84580 | C84: MOUSE TOY WITH PINK T-SHIRT | D84: 2 | E84: 40469.712 | F84: 3.75 | G84: 15710 | H84: United Kingdom | I84: =(D84 *F84) -> 7.5
A85: 496008 | B85: 21428 | C85: SET3 BOOK BOX GREEN GINGHAM FLOWER | D85: 4 | E85: 40206.525 | F85: 4.25 | G85: 14911 | H85: Eire | I85: =(D85 *F85) -> 17
A86: 509071 | B86: 84839 | C86: SWEETHEART KEY CABINET | D86: 2 | E86: 40318.487 | F86: 6.75 | G86: 16471 | H86: United Kingdom | I86: =(D86 *F86) -> 13.5
A87: 535656 | B87: 21986 | C87: PACK OF 12 PINK POLKADOT TISSUES | D87: 3 | E87: 40510.472 | F87: 0.29 | G87: 16010 | H87: United Kingdom | I87: =(D87 *F87) -> 0.87
A88: 522885 | B88: 21535 | C88: RED RETROSPOT SMALL MILK JUG | D88: 6 | E88: 40438.504 | F88: 2.55 | G88: 13952 | H88: United Kingdom | I88: =(D88 *F88) -> 15.3
A89: 502038 | B89: 20749 | C89: ASSORTED COLOUR MINI CASES | D89: 2 | E89: 40259.576 | F89: 7.95 | G89: 13206 | H89: United Kingdom | I89: =(D89 *F89) -> 15.9
A90: 516132 | B90: 22139 | C90: RETRO SPOT TEA SET CERAMIC 11 PC | D90: 12 | E90: 40375.644 | F90: 4.95 | G90: 16767 | H90: United Kingdom | I90: =(D90 *F90) -> 59.4
A91: 511500 | B91: 21216 | C91: SET 3 RED SPOT TIN TEA,COFFEE,SUGAR | D91: 4 | E91: 40337.614 | F91: 4.95 | G91: 14210 | H91: United Kingdom | I91: =(D91 *F91) -> 19.8
A92: 518547 | B92: 21426 | C92: WOODLAND STORAGE BOX SMALL | D92: 96 | E92: 40399.771 | F92: 1.25 | G92: 18102 | H92: United Kingdom | I92: =(D92 *F92) -> 120
A93: 501689 | B93: 22021 | C93: BLUE FELT EASTER EGG BASKET | D93: 12 | E93: 40255.712 | F93: 1.65 | G93: 15738 | H93: United Kingdom | I93: =(D93 *F93) -> 19.8
A94: 489802 | B94: 85104 | C94: SILVER GLASS T-LIGHT SET | D94: 4 | E94: 40149.522 | F94: 2.95 | G94: 15581 | H94: United Kingdom | I94: =(D94 *F94) -> 11.8
A95: 497364 | B95: 84997B | C95: RED 3 PIECE MINI DOTS CUTLERY SET | D95: 6 | E95: 40218.408 | F95: 3.75 | G95: 13131 | H95: United Kingdom | I95: =(D95 *F95) -> 22.5
A96: 535332 | B96: 84879 | C96: ASSORTED COLOUR BIRD ORNAMENT | D96: 8 | E96: 40507.663 | F96: 1.69 | G96: 18161 | H96: United Kingdom | I96: =(D96 *F96) -> 13.52
A97: 513953 | B97: 21043 | C97: APRON MODERN VINTAGE COTTON | D97: 3 | E97: 40358.593 | F97: 5.95 | G97: 14426 | H97: United Kingdom | I97: =(D97 *F97) -> 17.85
A98: 494359 | B98: 21730 | C98: GLASS STAR FROSTED T-LIGHT HOLDER | D98: 2 | E98: 40191.642 | F98: 4.95 | G98: 17962 | H98: United Kingdom | I98: =(D98 *F98) -> 9.9
A99: 533376 | B99: 22113 | C99: GREY HEART HOT WATER BOTTLE | D99: 12 | E99: 40499.444 | F99: 3.75 | G99: 15640 | H99: United Kingdom | I99: =(D99 *F99) -> 45
A100: 536975 | B100: 21888 | C100: BINGO SET | D100: 4 | E100: 40515.586 | F100: 3.75 | G100: 14911 | H100: Eire | I100: =(D100 *F100) -> 15
...

Sheet Task 2 Analysis
A1: SECTION 4: REVENUE BY COUNTRY
A2: UNITED KINGDOM
A4: SECTION 5: TRANSACTION BY COUNTRY
A5: UNITED KINGDOM
A7: SECTION 6: AVERAGE REVENUE BY COUNTRY
A8: EIRE
A10: SECTION 7: PIVOT TABLE 1
A11: UNITED KINGDOM
A12: DENMARK
A13: NETHERLANDS
A14: EIRE
A15: FRANCE
... A25: 5. small number of product generated large proportion of the total revenue

Sheet Revenue by Country
A3: Row Labels | B3: Sum of Revenue
A4: United Kingdom | B4: 16714.89
A5: Denmark | B5: 1083.6
A6: Netherlands | B6: 872.13
A7: Eire | B7: 842
A8: France | B8: 735.76
A9: Germany | B9: 466.5
A10: Sweden | B10: 155.64
A11: Portugal | B11: 129.3
A12: Japan | B12: 127.5
A13: Un Ited Kingdom | B13: 71.25
A14: Channel Islands | B14: 68.98
A15: Belgium | B15: 64.5
... A27: Grand Total | B27: 21603.28

Sheet Product Revenue
A3: Row Labels | B3: Sum of Revenue
A4: ASSORTED FARMYARD ANIMALS IN BUCKET | B4: 993.6
A5: GOLD WINE GLASS | B5: 976.32
A6: RUSTIC WOODEN CABINET, GLASS DOORS | B6: 573.92
A7: CHILDS BREAKFAST SET CIRCUS PARADE | B7: 397.8
A8: JUMBO SHOPPER VINTAGE RED PAISLEY | B8: 388.5
A9: EDWARDIAN PARASOL BLACK | B9: 362.45
A10: RECIPE BOX WITH METAL HEART | B10: 349.5
A11: BLUE POLKADOT PUDDING BOWL | B11: 324.48
A12: SET/10 RED SPOTTY PARTY CANDLES | B12: 305.28
A13: ROUND SNACK BOXES SET OF 4 FRUITS | B13: 244.8
A14: WHITE HANGING HEART T-LIGHT HOLDER | B14: 240.9
A15: RETROSPOT HEART HOT WATER BOTTLE | B15: 204
... A726: Grand Total | B726: 21603.28

Sheet README
A1: Country | B1: Total Revenue | C1: Number of Transaction | D1: Average Revenue
A2: Eire | B2: =SUMIF('Clean Data'!H:H,"Eire", 'Clean Data'!I:I) -> 842 | C2: =COUNTIF('Clean Data'!H:H,"Eire") -> 18 | D2: =AVERAGEIF('Clean Data'!H:H,"Eire", 'Clean Data'!I:I) -> 46.777778
A3: United Kingdom | B3: =SUMIF('Clean Data'!H:H,"United Kingdom", 'Clean Data'!I:I) -> 16714.89 | C3: =COUNTIF('Clean Data'!H:H,"United Kingdom") -> 876 | D3: =AVERAGEIF('Clean Data'!H:H,"United Kingdom", 'Clean Data'!I:I) -> 19.080925
A4: Germany | B4: =SUMIF('Clean Data'!H:H,"Germany", 'Clean Data'!I:I) -> 466.5 | C4: =COUNTIF('Clean Data'!H:H,"Germany") -> 19 | D4: =AVERAGEIF('Clean Data'!H:H,"Germany", 'Clean Data'!I:I) -> 24.552632
A5: France | B5: =SUMIF('Clean Data'!H:H,"France", 'Clean Data'!I:I) -> 735.76 | C5: =COUNTIF('Clean Data'!H:H,"France") -> 19 | D5: =AVERAGEIF('Clean Data'!H:H,"France", 'Clean Data'!I:I) -> 38.724211
A6: Belgium | B6: =SUMIF('Clean Data'!H:H,"Belgium", 'Clean Data'!I:I) -> 64.5 | C6: =COUNTIF('Clean Data'!H:H,"Belgium") -> 2 | D6: =AVERAGEIF('Clean Data'!H:H,"Belgium", 'Clean Data'!I:I) -> 32.25
